{
  "$schema": "./node_modules/@biomejs/biome/configuration_schema.json",
  "vcs": { "enabled": true, "clientKind": "git", "useIgnoreFile": true },
  "files": {
    "ignoreUnknown": true,
    "includes": ["**", "!**/node_modules", "!**/dist", "!**/coverage", "!**/.nx", "!**/.nx-cache"]
  },
  "formatter": {
    "enabled": true,
    "indentStyle": "space",
    "indentWidth": 2,
    "lineWidth": 100,
    "lineEnding": "lf"
  },
  "linter": {
    "enabled": true,
    "rules": {
      "recommended": true,
      "suspicious": {
        "noExplicitAny": "error"
      },
      "style": {
        "useImportType": "error",
        "useNodejsImportProtocol": "error"
      }
    }
  },
  "overrides": [
    {
      "includes": ["**/*.spec.ts", "**/*.test.ts"],
      "linter": {
        "rules": {
          "style": {
            "noNonNullAssertion": "off"
          }
        }
      }
    }
  ],
  "javascript": {
    "formatter": {
      "quoteStyle": "single",
      "semicolons": "asNeeded",
      "trailingCommas": "all",
      "arrowParentheses": "always"
    }
  }
}
